mcp_evaluation_server/__init__.py
mcp_evaluation_server/__main__.py
mcp_evaluation_server/config.py
mcp_evaluation_server/database.py
mcp_evaluation_server/exceptions.py
mcp_evaluation_server/main.py
mcp_evaluation_server/memory_protection.py
mcp_evaluation_server/models.py
mcp_evaluation_server/practical_security.py
mcp_evaluation_server/secure_config_manager.py
mcp_evaluation_server/secure_key_manager.py
mcp_evaluation_server/securekey_ext.c
mcp_evaluation_server/securekey_ext_setup.py
mcp_evaluation_server/simple_server.py
mcp_evaluation_server/tools.py
mcp_evaluation_server/utils.py
mcp_evaluation_server-0.2.10.dist-info/METADATA
mcp_evaluation_server-0.2.10.dist-info/WHEEL
mcp_evaluation_server-0.2.10.dist-info/entry_points.txt
mcp_evaluation_server-0.2.10.dist-info/licenses/LICENSE
mcp_evaluation_server-0.2.10.dist-info/RECORD
